xieyin/__init__.py
xieyin/pinmap0.bin
xieyin/pinmap1.bin
xieyin/utils.py
xieyin-0.0.3.dist-info/METADATA
xieyin-0.0.3.dist-info/WHEEL
xieyin-0.0.3.dist-info/top_level.txt
xieyin-0.0.3.dist-info/RECORD
