Metadata-Version: 2.1
Name: xieyin
Version: 0.0.3
Summary: Generate Chinese homophonic sentences
Home-page: UNKNOWN
Author: Chessom
Author-email: chessom@foxmail.com
License: MIT
Platform: UNKNOWN
Classifier: Programming Language :: Python :: 3
Classifier: License :: OSI Approved :: MIT License
Classifier: Operating System :: OS Independent
Requires-Python: >=3.4
Requires-Dist: pypinyin
Requires-Dist: jieba
